odoo/addons/project_task_pull_request_state/README.rst
odoo/addons/project_task_pull_request_state/__init__.py
odoo/addons/project_task_pull_request_state/__manifest__.py
odoo/addons/project_task_pull_request_state/i18n/it.po
odoo/addons/project_task_pull_request_state/i18n/project_task_pull_request_state.pot
odoo/addons/project_task_pull_request_state/models/__init__.py
odoo/addons/project_task_pull_request_state/models/project_project.py
odoo/addons/project_task_pull_request_state/models/project_task.py
odoo/addons/project_task_pull_request_state/models/res_config_settings.py
odoo/addons/project_task_pull_request_state/readme/CONFIGURE.md
odoo/addons/project_task_pull_request_state/readme/CONTEXT.md
odoo/addons/project_task_pull_request_state/readme/CONTRIBUTORS.md
odoo/addons/project_task_pull_request_state/readme/DESCRIPTION.md
odoo/addons/project_task_pull_request_state/static/description/icon.png
odoo/addons/project_task_pull_request_state/static/description/index.html
odoo/addons/project_task_pull_request_state/tests/__init__.py
odoo/addons/project_task_pull_request_state/tests/test_project_task_pull_request_state.py
odoo/addons/project_task_pull_request_state/views/project_project_view.xml
odoo/addons/project_task_pull_request_state/views/project_task_view.xml
odoo/addons/project_task_pull_request_state/views/res_config_settings_view.xml
odoo_addon_project_task_pull_request_state-18.0.1.0.0.2.dist-info/METADATA
odoo_addon_project_task_pull_request_state-18.0.1.0.0.2.dist-info/WHEEL
odoo_addon_project_task_pull_request_state-18.0.1.0.0.2.dist-info/top_level.txt
odoo_addon_project_task_pull_request_state-18.0.1.0.0.2.dist-info/RECORD
