Metadata-Version: 2.1
Name: odoo-addon-project_task_pull_request_state
Version: 18.0.1.0.0.2
Requires-Python: >=3.10
Requires-Dist: odoo-addon-project_task_pull_request==18.0.*
Requires-Dist: odoo==18.0.*
Summary: Track Pull Request state in tasks
Home-page: https://github.com/OCA/project
License: AGPL-3
Author: Cetmix, Odoo Community Association (OCA)
Author-email: support@odoo-community.org
Classifier: Programming Language :: Python
Classifier: Framework :: Odoo
Classifier: Framework :: Odoo :: 18.0
Classifier: License :: OSI Approved :: GNU Affero General Public License v3
